<?xml version="1.0" encoding="utf-8" ?>
<dwsync>
<file name="Deserializer.php" server="ftp.temperomidia.com.br//cirocontrade!/" local="130371558305902341" remote="130376980800000000" />
<file name="Serializer.php" server="ftp.temperomidia.com.br//cirocontrade!/" local="130371558305962345" remote="130376980800000000" />
<file name="Deserializer.php" server="ftp.temperomidia.com.br//cirocontrade/" local="130371558305902341" remote="130379188200000000" />
<file name="Serializer.php" server="ftp.temperomidia.com.br//cirocontrade/" local="130371558305962345" remote="130379188200000000" />
<file name="Deserializer.php" server="ftp.temperomidia.com.br" local="130371558305902341" remote="130380352200000000" />
<file name="Serializer.php" server="ftp.temperomidia.com.br" local="130371558305962345" remote="130380352200000000" />
<file name="Deserializer.php" server="ftp.tm11.hospedagemdesites.ws//public_html/dotz/" local="130371558305902341" remote="130530677400000000" />
<file name="Serializer.php" server="ftp.tm11.hospedagemdesites.ws//public_html/dotz/" local="130371558305962345" remote="130530678000000000" />
</dwsync>