<?xml version="1.0" encoding="utf-8" ?>
<dwsync>
<file name="Abstract.php" server="ftp.temperomidia.com.br//cirocontrade!/" local="130371558742617320" remote="130377020400000000" />
<file name="Exception.php" server="ftp.temperomidia.com.br//cirocontrade!/" local="130371558742667323" remote="130377020400000000" />
<file name="Interface.php" server="ftp.temperomidia.com.br//cirocontrade!/" local="130371558749337704" remote="130377021600000000" />
<file name="Stream.php" server="ftp.temperomidia.com.br//cirocontrade!/" local="130371558751017800" remote="130377021600000000" />
<file name="Abstract.php" server="ftp.temperomidia.com.br//cirocontrade/" local="130371558742617320" remote="130379196600000000" />
<file name="Exception.php" server="ftp.temperomidia.com.br//cirocontrade/" local="130371558742667323" remote="130379196600000000" />
<file name="Interface.php" server="ftp.temperomidia.com.br//cirocontrade/" local="130371558749337704" remote="130379196600000000" />
<file name="Stream.php" server="ftp.temperomidia.com.br//cirocontrade/" local="130371558751017800" remote="130379196600000000" />
</dwsync>